README.md
setup.py
ezviz/__init__.py
ezviz/__main__.py
ezviz/camera.py
ezviz/client.py
ezviz.egg-info/PKG-INFO
ezviz.egg-info/SOURCES.txt
ezviz.egg-info/dependency_links.txt
ezviz.egg-info/entry_points.txt
ezviz.egg-info/requires.txt
ezviz.egg-info/top_level.txt