Metadata-Version: 1.0
Name: ezviz
Version: 0.1.5.5
Summary: Pilot your Ezviz cameras
Home-page: http://github.com/williamluke4/pyEzviz/
Author: William Luke
Author-email: william@atto-byte.com
License: Apache Software License
Platform: UNKNOWN
